ml_workbench/__init__.py
ml_workbench/cli_experiment.py
ml_workbench/config.py
ml_workbench/dataset.py
ml_workbench/experiment.py
ml_workbench/feature.py
ml_workbench/mlflow_conf.py
ml_workbench/model.py
ml_workbench/runner.py
ml_workbench-0.2.6.dist-info/METADATA
ml_workbench-0.2.6.dist-info/WHEEL
ml_workbench-0.2.6.dist-info/entry_points.txt
ml_workbench-0.2.6.dist-info/RECORD
