Metadata-Version: 2.4
Name: ml-workbench
Version: 0.2.6
Summary: Local ML workbench configured for Databricks using uv
Author: Pheno
License: MIT
Requires-Python: >=3.12.0
Requires-Dist: boto3>=1.42.22
Requires-Dist: matplotlib>=3.10.8
Requires-Dist: mlflow>=3.8.1
Requires-Dist: numpy>=1.26.4
Requires-Dist: pandas>=2.3.3
Requires-Dist: pyyaml
Requires-Dist: scikit-learn>=1.8.0
Requires-Dist: seaborn
